ckanext_subscribe-1.1.0-py2.7-nspkg.pth
ckanext/subscribe/__init__.py
ckanext/subscribe/action.py
ckanext/subscribe/auth.py
ckanext/subscribe/cli.py
ckanext/subscribe/controller.py
ckanext/subscribe/dictization.py
ckanext/subscribe/email_auth.py
ckanext/subscribe/email_verification.py
ckanext/subscribe/interfaces.py
ckanext/subscribe/mailer.py
ckanext/subscribe/model.py
ckanext/subscribe/notification.py
ckanext/subscribe/notification_email.py
ckanext/subscribe/plugin.py
ckanext/subscribe/schema.py
ckanext/subscribe/utils.py
ckanext/subscribe/fanstatic/subscribe.css
ckanext/subscribe/templates/group/snippets/info.html
ckanext/subscribe/templates/package/snippets/info.html
ckanext/subscribe/templates/snippets/organization.html
ckanext/subscribe/templates/subscribe/manage.html
ckanext/subscribe/templates/subscribe/request_manage_code.html
ckanext/subscribe/tests/__init__.py
ckanext/subscribe/tests/factories.py
ckanext/subscribe/tests/test_action.py
ckanext/subscribe/tests/test_auth.py
ckanext/subscribe/tests/test_controller.py
ckanext/subscribe/tests/test_email_verification.py
ckanext/subscribe/tests/test_notification.py
ckanext/subscribe/tests/test_notification_email.py
ckanext_subscribe-1.1.0.dist-info/LICENSE
ckanext_subscribe-1.1.0.dist-info/METADATA
ckanext_subscribe-1.1.0.dist-info/WHEEL
ckanext_subscribe-1.1.0.dist-info/entry_points.txt
ckanext_subscribe-1.1.0.dist-info/namespace_packages.txt
ckanext_subscribe-1.1.0.dist-info/top_level.txt
ckanext_subscribe-1.1.0.dist-info/RECORD
