Metadata-Version: 2.1
Name: ckanext-subscribe
Version: 1.1.0
Summary: CKAN extension that allows users to subscribe to updates WITHOUT requiring loginn
Home-page: https://github.com/davidread/ckanext-subscribe
Author: David Read
Author-email: david.read@hackneyworkshop.com
License: AGPL
Keywords: CKAN email subscription notifications
Platform: UNKNOWN
Classifier: Development Status :: 4 - Beta
Classifier: License :: OSI Approved :: GNU Affero General Public License v3 or later (AGPLv3+)
Classifier: Programming Language :: Python :: 3
Requires-Dist: enum34
